Metadata-Version: 1.1
Name: logable
Version: 1.0a1.dev0
Summary: logable
Home-page: https://git.xdelta.capital/Extensions/logable.git
Author: UNKNOWN
Author-email: UNKNOWN
License: UNKNOWN
Download-URL: https://git.xdelta.capital/Extensions/logable/archive/logable.tar.gz
Keywords: logable
Platform: UNKNOWN
